[
  {
    "Exercise Name": "Back Lever",
    "Primary Muscle": "Core",
    "Secondary Muscles": "Back, Shoulders",
    "Exercise Type": "Compound",
    "Equipment": "Bodyweight",
    "Workout Type": "Core",
    "Progression": "Progressive Overload"
  },
  {
    "Exercise Name": "Back Squat",
    "Primary Muscle": "Quads",
    "Secondary Muscles": "Glutes, Hamstrings, Core",
    "Exercise Type": "Compound",
    "Equipment": "Barbell",
    "Workout Type": "Full Body Strength, Lower Body Strength, Push/Pull/Legs",
    "Progression": "Progressive Overload",
    "Webp File": "back-squat.webp"
  },
  {
    "Exercise Name": "Barbell Belt Squat",
    "Primary Muscle": "Quads",
    "Secondary Muscles": "Glutes, Hamstrings, Core",
    "Exercise Type": "Compound",
    "Equipment": "Barbell",
    "Workout Type": "Lower Body Strength",
    "Progression": "Progressive Overload"
  },
  {
    "Exercise Name": "Barbell Bench Press",
    "Primary Muscle": "Chest",
    "Secondary Muscles": "Front Delts, Triceps",
    "Exercise Type": "Compound",
    "Equipment": "Barbell",
    "Workout Type": "Full Body Strength, Upper Body Strength, Push/Pull/Legs",
    "Progression": "Progressive Overload",
    "Webp File": "barbell-bench-press.webp"
  },
  {
    "Exercise Name": "Barbell Bent-Over Row",
    "Primary Muscle": "Lats",
    "Secondary Muscles": "Biceps, Lower Back, Core",
    "Exercise Type": "Compound",
    "Equipment": "Barbell",
    "Workout Type": "Full Body Strength, Upper Body Strength, Push/Pull/Legs",
    "Progression": "Progressive Overload",
    "Webp File": "barbell-bent-over-row.webp"
  },
  {
    "Exercise Name": "Barbell Bicep Curl",
    "Primary Muscle": "Biceps",
    "Secondary Muscles": "Front Delts, Forearms",
    "Exercise Type": "Isolation",
    "Equipment": "Barbell",
    "Workout Type": "Upper Body Strength",
    "Progression": "Progressive Overload",
    "Webp File": "barbell-bicep-curl.webp"
  },
  {
    "Exercise Name": "Barbell Close Grip Bench Press",
    "Primary Muscle": "Triceps",
    "Secondary Muscles": "Chest, Front Delts",
    "Exercise Type": "Compound",
    "Equipment": "Barbell",
    "Workout Type": "Upper Body Strength",
    "Progression": "Progressive Overload"
  },
  {
    "Exercise Name": "Barbell Deadlift",
    "Primary Muscle": "Hamstrings",
    "Secondary Muscles": "Glutes, Lower Back, Quads",
    "Exercise Type": "Compound",
    "Equipment": "Barbell",
    "Workout Type": "Full Body Strength, Lower Body Strength, Push/Pull/Legs",
    "Progression": "Progressive Overload",
    "Webp File": "barbell-deadlift.webp"
  },

  {
    "Exercise Name": "Barbell Front Squat",
    "Primary Muscle": "Quads",
    "Secondary Muscles": "Core, Glutes, Upper Back",
    "Exercise Type": "Compound",
    "Equipment": "Barbell",
    "Workout Type": "Lower Body Strength, Push/Pull/Legs",
    "Progression": "Progressive Overload",
    "Webp File": "front-squat.webp"
  },
  {
    "Exercise Name": "Barbell Good Morning",
    "Primary Muscle": "Glutes",
    "Secondary Muscles": "Hamstrings, Lower Back, Core",
    "Exercise Type": "Compound",
    "Equipment": "Barbell",
    "Workout Type": "Lower Body Strength",
    "Progression": "Progressive Overload",
    "Webp File": "good-morning.webp"
  },
  {
    "Exercise Name": "Barbell Hack Squat",
    "Primary Muscle": "Quads",
    "Secondary Muscles": "Glutes, Hamstrings",
    "Exercise Type": "Compound",
    "Equipment": "Barbell",
    "Workout Type": "Lower Body Strength",
    "Progression": "Progressive Overload"
  },
  {
    "Exercise Name": "Barbell High Pull",
    "Primary Muscle": "Traps",
    "Secondary Muscles": "Delts, Hamstrings",
    "Exercise Type": "Compound",
    "Equipment": "Barbell",
    "Workout Type": "Cardio, HIIT",
    "Progression": "Power Development"
  },
  {
    "Exercise Name": "Barbell Hip Thrust",
    "Webp File": "barbell-hip-thrust.webp",
    "Primary Muscle": "Glutes",
    "Secondary Muscles": "Hamstrings, Lower Back, Quads",
    "Exercise Type": "Compound",
    "Equipment": "Barbell",
    "Workout Type": "Lower Body Strength",
    "Progression": "Progressive Overload"
  },
  {
    "Exercise Name": "Barbell Incline Bench Press",
    "Primary Muscle": "Chest",
    "Secondary Muscles": "Front Delts, Triceps",
    "Exercise Type": "Compound",
    "Equipment": "Barbell",
    "Workout Type": "Upper Body Strength, Push/Pull/Legs",
    "Progression": "Progressive Overload",
    "Webp File": "incline-barbell-bench-press.webp"
  },
  {
    "Exercise Name": "Barbell Overhead Press",
    "Primary Muscle": "Delts",
    "Secondary Muscles": "Triceps, Chest, Core",
    "Exercise Type": "Compound",
    "Equipment": "Barbell",
    "Workout Type": "Upper Body Strength, Push/Pull/Legs",
    "Progression": "Progressive Overload",
    "Webp File": "barbell-overhead-press.webp"
  },
  {
    "Exercise Name": "Barbell Paused Bench Press",
    "Primary Muscle": "Chest",
    "Secondary Muscles": "Front Delts, Triceps",
    "Exercise Type": "Compound",
    "Equipment": "Barbell",
    "Workout Type": "Upper Body Strength",
    "Progression": "Progressive Overload",
    "Webp File": "barbell-paused-bench-press.webp"
  },
  {
    "Exercise Name": "Barbell Pendulum Squat",
    "Primary Muscle": "Quads",
    "Secondary Muscles": "Glutes, Hamstrings",
    "Exercise Type": "Compound",
    "Equipment": "Barbell",
    "Workout Type": "Lower Body Strength",
    "Progression": "Progressive Overload"
  },
  {
    "Exercise Name": "Barbell Pullover",
    "Webp File": "barbell-pullover.webp",
    "Primary Muscle": "Chest",
    "Secondary Muscles": "Lats, Triceps",
    "Exercise Type": "Compound",
    "Equipment": "Barbell",
    "Workout Type": "Upper Body Strength",
    "Progression": "Progressive Overload"
  },
  {
    "Exercise Name": "Barbell Push Press",
    "Primary Muscle": "Delts",
    "Secondary Muscles": "Triceps, Chest, Core",
    "Exercise Type": "Compound",
    "Equipment": "Barbell",
    "Workout Type": "Upper Body Strength",
    "Progression": "Progressive Overload",
    "Webp File": "barbell-push-press.webp"
  },
  {
    "Exercise Name": "Barbell Romanian Deadlift",
    "Primary Muscle": "Hamstrings",
    "Secondary Muscles": "Glutes, Lower Back",
    "Exercise Type": "Compound",
    "Equipment": "Barbell",
    "Workout Type": "Lower Body Strength, Push/Pull/Legs",
    "Progression": "Progressive Overload",
    "Webp File": "barbell-romanian-deadlift.webp"
  },
  {
    "Exercise Name": "Barbell Shrug",
    "Primary Muscle": "Traps",
    "Secondary Muscles": "Upper Back",
    "Exercise Type": "Compound",
    "Equipment": "Barbell",
    "Workout Type": "Upper Body Strength",
    "Progression": "Progressive Overload",
    "Webp File": "barbell-shrugs.webp"
  },


  {
    "Exercise Name": "Barbell Sumo Deadlift",
    "Primary Muscle": "Hamstrings",
    "Secondary Muscles": "Glutes, Quads, Lower Back, Adductors",
    "Exercise Type": "Compound",
    "Equipment": "Barbell",
    "Workout Type": "Lower Body Strength",
    "Progression": "Progressive Overload",
    "Webp File": "barbell-sumo-deadlift.webp"
  },
  {
    "Exercise Name": "Barbell Thruster",
    "Primary Muscle": "Quads",
    "Secondary Muscles": "Glutes, Delts, Triceps, Core",
    "Exercise Type": "Compound",
    "Equipment": "Barbell",
    "Workout Type": "Full Body Strength, HIIT",
    "Progression": "Power Development"
  },
  {
    "Exercise Name": "Barbell Trap Bar Deadlift",
    "Primary Muscle": "Hamstrings",
    "Secondary Muscles": "Glutes, Quads, Lower Back",
    "Exercise Type": "Compound",
    "Equipment": "Barbell",
    "Workout Type": "Lower Body Strength, Full Body Strength",
    "Progression": "Progressive Overload",
    "Webp File": "trap-bar-deadlift.webp"
  },
  {
    "Exercise Name": "Barbell Upright Row",
    "Primary Muscle": "Traps",
    "Secondary Muscles": "Delts, Biceps",
    "Exercise Type": "Compound",
    "Equipment": "Barbell",
    "Workout Type": "Upper Body Strength",
    "Progression": "Progressive Overload",
    "Webp File": "barbell-upright-row.webp"
  },
  {
    "Exercise Name": "Behind Neck Pulldown",
    "Webp File": "behind-neck-pulldown.webp",
    "Primary Muscle": "Lats",
    "Secondary Muscles": "Biceps, Core",
    "Exercise Type": "Compound",
    "Equipment": "Cable Machine",
    "Workout Type": "Upper Body Strength",
    "Progression": "Progressive Overload"
  },
  {
    "Exercise Name": "Bench Dip",
    "Primary Muscle": "Triceps",
    "Secondary Muscles": "Chest, Front Delts",
    "Exercise Type": "Compound",
    "Equipment": "Bodyweight",
    "Workout Type": "Upper Body Strength",
    "Progression": "Progressive Overload"
  },
  {
    "Exercise Name": "Bent Over Lateral Raise",
    "Webp File": "bent-over-lateral-raise.webp",
    "Primary Muscle": "",
    "Secondary Muscles": "",
    "Exercise Type": "Isolation",
    "Equipment": "Bodyweight",
    "Workout Type": "",
    "Progression": "Progressive Overload"
  },
  {
    "Exercise Name": "Bicycle Crunch",
    "Primary Muscle": "Core",
    "Secondary Muscles": "Obliques, Hip Flexors",
    "Exercise Type": "Compound",
    "Equipment": "Bodyweight",
    "Workout Type": "Core",
    "Progression": "Progressive Overload"
  },
  {
    "Exercise Name": "Bird Dog",
    "Primary Muscle": "Core",
    "Secondary Muscles": "Glutes, Lower Back",
    "Exercise Type": "Compound",
    "Equipment": "Bodyweight",
    "Workout Type": "Core",
    "Progression": "Progressive Overload"
  },
  {
    "Exercise Name": "Bodyweight Squat",
    "Webp File": "bodyweight-squat.webp",
    "Primary Muscle": "Quads",
    "Secondary Muscles": "Glutes, Hamstrings, Core",
    "Exercise Type": "Compound",
    "Equipment": "Bodyweight",
    "Workout Type": "Lower Body Strength",
    "Progression": "Progressive Overload"
  },

  {
    "Exercise Name": "Bulgarian Split Squat",
    "Primary Muscle": "Quads",
    "Secondary Muscles": "Glutes, Hamstrings, Core",
    "Exercise Type": "Compound",
    "Equipment": "Bodyweight",
    "Workout Type": "Lower Body Strength",
    "Progression": "Progressive Overload",
    "Webp File": "bodyweight-bulgarian-split-squat.webp"
  },


  {
    "Exercise Name": "Cable Pull-Up",
    "Primary Muscle": "Lats",
    "Secondary Muscles": "Biceps, Rear Delts, Core",
    "Exercise Type": "Compound",
    "Equipment": "Cable Machine",
    "Workout Type": "Upper Body Strength, Full Body Strength",
    "Progression": "Progressive Overload"
  },
  {
    "Exercise Name": "Cable Skull Crusher",
    "Primary Muscle": "Triceps",
    "Secondary Muscles": "Front Delts, Chest",
    "Exercise Type": "Isolation",
    "Equipment": "Cable Machine",
    "Workout Type": "Upper Body Strength",
    "Progression": "Progressive Overload"
  },
  {
    "Exercise Name": "Cable Tricep Extension",
    "Primary Muscle": "Triceps",
    "Secondary Muscles": "Front Delts, Chest",
    "Exercise Type": "Isolation",
    "Equipment": "Cable Machine",
    "Workout Type": "Upper Body Strength",
    "Progression": "Progressive Overload"
  },
  {
    "Exercise Name": "Calf Raise",
    "Primary Muscle": "Calves",
    "Secondary Muscles": "Core",
    "Exercise Type": "Isolation",
    "Equipment": "Bodyweight",
    "Workout Type": "Lower Body Strength",
    "Progression": "Progressive Overload"
  },
  {
    "Exercise Name": "Chin-Up",
    "Primary Muscle": "Biceps",
    "Secondary Muscles": "Lats, Core, Delts",
    "Exercise Type": "Compound",
    "Equipment": "Bodyweight",
    "Workout Type": "Upper Body Strength",
    "Progression": "Progressive Overload"
  },
  {
    "Exercise Name": "Close Grip Bench Press",
    "Webp File": "close-grip-bench-press.webp",
    "Primary Muscle": "Chest",
    "Secondary Muscles": "Front Delts, Triceps",
    "Exercise Type": "Compound",
    "Equipment": "Bodyweight",
    "Workout Type": "Upper Body Strength",
    "Progression": "Progressive Overload"
  },
  {
    "Exercise Name": "Close Grip Lat Pulldown",
    "Primary Muscle": "Lats",
    "Secondary Muscles": "Biceps, Rhomboids, Traps",
    "Exercise Type": "Compound",
    "Equipment": "Cable Machine",
    "Workout Type": "Upper Body Strength, Push/Pull/Legs",
    "Progression": "Progressive Overload",
    "Webp File": "close-grip-pulldown.webp"
  },

  {
    "Exercise Name": "Crunch",
    "Primary Muscle": "Core",
    "Secondary Muscles": "Hip Flexors",
    "Exercise Type": "Isolation",
    "Equipment": "Bodyweight",
    "Workout Type": "Core",
    "Progression": "Progressive Overload"
  },
  
  {
    "Exercise Name": "Decline Push-Up",
    "Primary Muscle": "Chest",
    "Secondary Muscles": "Front Delts, Triceps",
    "Exercise Type": "Compound",
    "Equipment": "Bodyweight",
    "Workout Type": "Upper Body Strength",
    "Progression": "Progressive Overload"
  },
  {
    "Exercise Name": "Diamond Push-Up",
    "Primary Muscle": "Triceps",
    "Secondary Muscles": "Chest, Front Delts",
    "Exercise Type": "Compound",
    "Equipment": "Bodyweight",
    "Workout Type": "Upper Body Strength",
    "Progression": "Progressive Overload"
  },
  {
    "Exercise Name": "Dip",
    "Primary Muscle": "Triceps",
    "Secondary Muscles": "Chest, Front Delts",
    "Exercise Type": "Compound",
    "Equipment": "Bodyweight",
    "Workout Type": "Upper Body Strength",
    "Progression": "Progressive Overload"
  },
  {
    "Exercise Name": "Dumbbell Arnold Press",
    "Primary Muscle": "Delts",
    "Secondary Muscles": "Triceps, Chest",
    "Exercise Type": "Compound",
    "Equipment": "Dumbbell",
    "Workout Type": "Upper Body Strength",
    "Progression": "Progressive Overload"
  },
  {
    "Exercise Name": "Dumbbell Bench Press",
    "Primary Muscle": "Chest",
    "Secondary Muscles": "Front Delts, Triceps",
    "Exercise Type": "Compound",
    "Equipment": "Dumbbell",
    "Workout Type": "Upper Body Strength, Full Body Strength",
    "Progression": "Progressive Overload",
    "Webp File": "dumbbell-bench-press.webp"
  },
  {
    "Exercise Name": "Dumbbell Bent-Over Row",
    "Primary Muscle": "Lats",
    "Secondary Muscles": "Biceps, Core",
    "Exercise Type": "Compound",
    "Equipment": "Dumbbell",
    "Workout Type": "Upper Body Strength, Full Body Strength",
    "Progression": "Progressive Overload",
    "Webp File": "dumbbell-bent-over-row.webp"
  },
  {
    "Exercise Name": "Dumbbell Bicep Curl",
    "Primary Muscle": "Biceps",
    "Secondary Muscles": "Front Delts, Forearms",
    "Exercise Type": "Isolation",
    "Equipment": "Dumbbell",
    "Workout Type": "Upper Body Strength",
    "Progression": "Progressive Overload"
  },
  {
    "Exercise Name": "Dumbbell Bulgarian Split Squat",
    "Primary Muscle": "Quads",
    "Secondary Muscles": "Glutes, Hamstrings, Core",
    "Exercise Type": "Compound",
    "Equipment": "Dumbbell",
    "Workout Type": "Lower Body Strength",
    "Progression": "Progressive Overload",
    "Webp File": "barbell-bulgarian-split-squat.webp"
  },
  {
    "Exercise Name": "Dumbbell Close Grip Bench Press",
    "Primary Muscle": "Triceps",
    "Secondary Muscles": "Chest, Front Delts",
    "Exercise Type": "Compound",
    "Equipment": "Dumbbell",
    "Workout Type": "Upper Body Strength",
    "Progression": "Progressive Overload"
  },
  {
    "Exercise Name": "Dumbbell Concentration Curl",
    "Webp File": "dumbbell-concentration-curl.webp",
    "Primary Muscle": "Biceps",
    "Secondary Muscles": "Front Delts, Forearms",
    "Exercise Type": "Isolation",
    "Equipment": "Dumbbell",
    "Workout Type": "Upper Body Strength",
    "Progression": "Progressive Overload"
  },
  {
    "Exercise Name": "Dumbbell Deadlift",
    "Primary Muscle": "Hamstrings",
    "Secondary Muscles": "Glutes, Quads, Lower Back",
    "Exercise Type": "Compound",
    "Equipment": "Dumbbell",
    "Workout Type": "Lower Body Strength, Full Body Strength",
    "Progression": "Progressive Overload",
    "Webp File": "dumbbell-deadlift.webp"
  },

  {
    "Exercise Name": "Dumbbell Farmer Carry",
    "Primary Muscle": "Core",
    "Secondary Muscles": "Traps, Forearms",
    "Exercise Type": "Compound",
    "Equipment": "Dumbbell",
    "Workout Type": "Core",
    "Progression": "Progressive Overload"
  },
  {
    "Exercise Name": "Dumbbell Fly",
    "Primary Muscle": "Chest",
    "Secondary Muscles": "Front Delts",
    "Exercise Type": "Isolation",
    "Equipment": "Dumbbell",
    "Workout Type": "Upper Body Strength",
    "Progression": "Progressive Overload",
    "Webp File": "dumbbell-fly.webp"
  },
  {
    "Exercise Name": "Dumbbell Front Raise",
    "Primary Muscle": "Delts",
    "Secondary Muscles": "Chest",
    "Exercise Type": "Isolation",
    "Equipment": "Dumbbell",
    "Workout Type": "Upper Body Strength",
    "Progression": "Progressive Overload",
    "Webp File": "dumbbell-front-raise.webp"
  },
  {
    "Exercise Name": "Dumbbell Front Squat",
    "Primary Muscle": "Quads",
    "Secondary Muscles": "Glutes, Core, Upper Back",
    "Exercise Type": "Compound",
    "Equipment": "Dumbbell",
    "Workout Type": "Lower Body Strength",
    "Progression": "Progressive Overload"
  },
  {
    "Exercise Name": "Dumbbell Goblet Squat",
    "Primary Muscle": "Quads",
    "Secondary Muscles": "Glutes, Core",
    "Exercise Type": "Compound",
    "Equipment": "Dumbbell",
    "Workout Type": "Lower Body Strength, Full Body Strength",
    "Progression": "Progressive Overload",
    "Webp File": "dumbbell-goblet-squat.webp"
  },
  {
    "Exercise Name": "Dumbbell Hammer Curl",
    "Primary Muscle": "Biceps",
    "Secondary Muscles": "Forearms",
    "Exercise Type": "Isolation",
    "Equipment": "Dumbbell",
    "Workout Type": "Upper Body Strength",
    "Progression": "Progressive Overload",
    "Webp File": "hammer-curl.webp"
  },
  {
    "Exercise Name": "Dumbbell Incline Bench Press",
    "Primary Muscle": "Chest",
    "Secondary Muscles": "Front Delts, Triceps",
    "Exercise Type": "Compound",
    "Equipment": "Dumbbell",
    "Workout Type": "Upper Body Strength",
    "Progression": "Progressive Overload",
    "Webp File": "incline-dumbbell-bench-press.webp"
  },
  {
    "Exercise Name": "Dumbbell Incline Curl",
    "Primary Muscle": "Biceps",
    "Secondary Muscles": "Front Delts",
    "Exercise Type": "Isolation",
    "Equipment": "Dumbbell",
    "Workout Type": "Upper Body Strength",
    "Progression": "Progressive Overload",
    "Webp File": "incline-dumbbell-curl.webp"
  },
  {
    "Exercise Name": "Dumbbell Jump Squat",
    "Primary Muscle": "Quads",
    "Secondary Muscles": "Glutes, Core, Calves",
    "Exercise Type": "Compound",
    "Equipment": "Dumbbell",
    "Workout Type": "Lower Body Strength, HIIT",
    "Progression": "Power Development"
  },
  {
    "Exercise Name": "Dumbbell Kickback",
    "Primary Muscle": "Triceps",
    "Secondary Muscles": "Shoulders",
    "Exercise Type": "Isolation",
    "Equipment": "Dumbbell",
    "Workout Type": "Upper Body Strength",
    "Progression": "Progressive Overload"
  },
  {
    "Exercise Name": "Dumbbell Lateral Raise",
    "Primary Muscle": "Delts",
    "Secondary Muscles": "Traps",
    "Exercise Type": "Isolation",
    "Equipment": "Dumbbell",
    "Workout Type": "Upper Body Strength",
    "Progression": "Progressive Overload",
    "Webp File": "dumbbell-lateral-raise.webp"
  },
  {
    "Exercise Name": "Dumbbell Lunge",
    "Primary Muscle": "Quads",
    "Secondary Muscles": "Glutes, Hamstrings, Core",
    "Exercise Type": "Compound",
    "Equipment": "Dumbbell",
    "Workout Type": "Lower Body Strength",
    "Progression": "Progressive Overload"
  },
  {
    "Exercise Name": "Dumbbell Overhead Tricep Extension",
    "Primary Muscle": "Triceps",
    "Secondary Muscles": "Shoulders, Chest",
    "Exercise Type": "Isolation",
    "Equipment": "Dumbbell",
    "Workout Type": "Upper Body Strength",
    "Progression": "Progressive Overload"
  },

  {
    "Exercise Name": "Dumbbell Pullover",
    "Primary Muscle": "Chest",
    "Secondary Muscles": "Lats, Triceps",
    "Exercise Type": "Isolation",
    "Equipment": "Dumbbell",
    "Workout Type": "Upper Body Strength",
    "Progression": "Progressive Overload",
    "Webp File": "dumbbell-pullover.webp"
  },
  {
    "Exercise Name": "Dumbbell Renegade Row",
    "Primary Muscle": "Core",
    "Secondary Muscles": "Lats, Triceps, Shoulders",
    "Exercise Type": "Compound",
    "Equipment": "Dumbbell",
    "Workout Type": "Full Body Strength, HIIT",
    "Progression": "Progressive Overload"
  },
  {
    "Exercise Name": "Dumbbell Reverse Fly",
    "Primary Muscle": "Rear Delts",
    "Secondary Muscles": "Upper Back",
    "Exercise Type": "Isolation",
    "Equipment": "Dumbbell",
    "Workout Type": "Upper Body Strength",
    "Progression": "Progressive Overload"
  },
  {
    "Exercise Name": "Dumbbell Reverse Lunge",
    "Primary Muscle": "Quads",
    "Secondary Muscles": "Glutes, Hamstrings, Core",
    "Exercise Type": "Compound",
    "Equipment": "Dumbbell",
    "Workout Type": "Lower Body Strength",
    "Progression": "Progressive Overload"
  },
  {
    "Exercise Name": "Dumbbell Romanian Deadlift",
    "Primary Muscle": "Hamstrings",
    "Secondary Muscles": "Glutes, Lower Back",
    "Exercise Type": "Compound",
    "Equipment": "Dumbbell",
    "Workout Type": "Lower Body Strength",
    "Progression": "Progressive Overload",
    "Webp File": "dumbbell-romanian-deadlift.webp"
  },
  {
    "Exercise Name": "Dumbbell Shoulder Press",
    "Primary Muscle": "Delts",
    "Secondary Muscles": "Triceps, Chest, Core",
    "Exercise Type": "Compound",
    "Equipment": "Dumbbell",
    "Workout Type": "Upper Body Strength, Full Body Strength",
    "Progression": "Progressive Overload",
    "Webp File": "dumbbell-shoulder-press.webp"
  },
  {
    "Exercise Name": "Dumbbell Shrug",
    "Webp File": "dumbbell-shrug.webp",
    "Primary Muscle": "Traps",
    "Secondary Muscles": "Upper Back",
    "Exercise Type": "Compound",
    "Equipment": "Dumbbell",
    "Workout Type": "Upper Body Strength",
    "Progression": "Progressive Overload"
  },
  {
    "Exercise Name": "Dumbbell Single-Arm Row",
    "Primary Muscle": "Lats",
    "Secondary Muscles": "Biceps, Core, Obliques",
    "Exercise Type": "Compound",
    "Equipment": "Dumbbell",
    "Workout Type": "Upper Body Strength",
    "Progression": "Progressive Overload",
    "Webp File": "dumbbell-bent-over-row-single-arm.webp"
  },

  {
    "Exercise Name": "Dumbbell Single-Leg Deadlift",
    "Primary Muscle": "Hamstrings",
    "Secondary Muscles": "Glutes, Core, Balance",
    "Exercise Type": "Compound",
    "Equipment": "Dumbbell",
    "Workout Type": "Lower Body Strength",
    "Progression": "Progressive Overload"
  },
  {
    "Exercise Name": "Dumbbell Step-Up",
    "Primary Muscle": "Quads",
    "Secondary Muscles": "Glutes, Hamstrings",
    "Exercise Type": "Compound",
    "Equipment": "Dumbbell",
    "Workout Type": "Lower Body Strength",
    "Progression": "Progressive Overload"
  },
  {
    "Exercise Name": "Dumbbell Suitcase Deadlift",
    "Primary Muscle": "Core",
    "Secondary Muscles": "Obliques, Lower Back, Glutes",
    "Exercise Type": "Compound",
    "Equipment": "Dumbbell",
    "Workout Type": "Core",
    "Progression": "Progressive Overload"
  },
  {
    "Exercise Name": "Dumbbell Thruster",
    "Primary Muscle": "Quads",
    "Secondary Muscles": "Glutes, Delts, Triceps, Core",
    "Exercise Type": "Compound",
    "Equipment": "Dumbbell",
    "Workout Type": "Full Body Strength, HIIT",
    "Progression": "Power Development"
  },
  {
    "Exercise Name": "Dumbbell Walking Lunge",
    "Primary Muscle": "Quads",
    "Secondary Muscles": "Glutes, Hamstrings, Core",
    "Exercise Type": "Compound",
    "Equipment": "Dumbbell",
    "Workout Type": "Lower Body Strength, HIIT",
    "Progression": "Progressive Overload"
  },
  {
    "Exercise Name": "Flutter Kicks",
    "Primary Muscle": "Core",
    "Secondary Muscles": "Hip Flexors",
    "Exercise Type": "Isolation",
    "Equipment": "Bodyweight",
    "Workout Type": "Core",
    "Progression": "Progressive Overload"
  },
  {
    "Exercise Name": "Front Lever",
    "Primary Muscle": "Core",
    "Secondary Muscles": "Chest, Shoulders, Lats",
    "Exercise Type": "Compound",
    "Equipment": "Bodyweight",
    "Workout Type": "Core",
    "Progression": "Progressive Overload"
  },
  {
    "Exercise Name": "Glute Bridge",
    "Primary Muscle": "Glutes",
    "Secondary Muscles": "Hamstrings, Core",
    "Exercise Type": "Compound",
    "Equipment": "Bodyweight",
    "Workout Type": "Lower Body Strength",
    "Progression": "Progressive Overload"
  },


  {
    "Exercise Name": "Hanging Knee Raise",
    "Primary Muscle": "Core",
    "Secondary Muscles": "Hip Flexors, Chest",
    "Exercise Type": "Isolation",
    "Equipment": "Bodyweight",
    "Workout Type": "Core",
    "Progression": "Progressive Overload"
  },
 
  {
    "Exercise Name": "Hollow Body Hold",
    "Primary Muscle": "Core",
    "Secondary Muscles": "Shoulders, Back",
    "Exercise Type": "Compound",
    "Equipment": "Bodyweight",
    "Workout Type": "Core",
    "Progression": "Progressive Overload"
  },

  {
    "Exercise Name": "Incline Dumbbell Fly",
    "Webp File": "incline-dumbbell-fly.webp",
    "Primary Muscle": "Chest",
    "Secondary Muscles": "Front Delts, Triceps",
    "Exercise Type": "Isolation",
    "Equipment": "Dumbbell",
    "Workout Type": "Upper Body Strength",
    "Progression": "Progressive Overload"
  },

  {
    "Exercise Name": "Jump Squat",
    "Primary Muscle": "Quads",
    "Secondary Muscles": "Glutes, Core, Calves",
    "Exercise Type": "Compound",
    "Equipment": "Bodyweight",
    "Workout Type": "Lower Body Strength, HIIT",
    "Progression": "Power Development",
    "Webp File": "jump-squat.webp"
  },

  {
    "Exercise Name": "Kettlebell Swing",
    "Primary Muscle": "Hamstrings",
    "Secondary Muscles": "Glutes, Core, Upper Back",
    "Exercise Type": "Compound",
    "Equipment": "Kettlebell",
    "Workout Type": "Lower Body Strength, Cardio, HIIT",
    "Progression": "Power Development",
    "Webp File": "kettlebell-swing.webp"
  },

  {
    "Exercise Name": "L-Sit",
    "Primary Muscle": "Core",
    "Secondary Muscles": "Shoulders, Triceps, Hip Flexors",
    "Exercise Type": "Compound",
    "Equipment": "Bodyweight",
    "Workout Type": "Core",
    "Progression": "Progressive Overload"
  },
  {
    "Exercise Name": "Landmine Deadlift",
    "Primary Muscle": "Hamstrings",
    "Secondary Muscles": "Glutes, Lower Back, Quads",
    "Exercise Type": "Compound",
    "Equipment": "Landmine",
    "Workout Type": "Lower Body Strength",
    "Progression": "Progressive Overload"
  },
  {
    "Exercise Name": "Landmine Press",
    "Primary Muscle": "Delts",
    "Secondary Muscles": "Triceps, Chest, Core",
    "Exercise Type": "Compound",
    "Equipment": "Landmine",
    "Workout Type": "Upper Body Strength",
    "Progression": "Progressive Overload"
  },
  {
    "Exercise Name": "Landmine Rotation",
    "Primary Muscle": "Core",
    "Secondary Muscles": "Obliques, Shoulders",
    "Exercise Type": "Compound",
    "Equipment": "Landmine",
    "Workout Type": "Core, HIIT",
    "Progression": "Progressive Overload"
  },
  {
    "Exercise Name": "Landmine Row",
    "Primary Muscle": "Lats",
    "Secondary Muscles": "Biceps, Core",
    "Exercise Type": "Compound",
    "Equipment": "Landmine",
    "Workout Type": "Upper Body Strength",
    "Progression": "Progressive Overload"
  },
  {
    "Exercise Name": "Landmine Squat",
    "Primary Muscle": "Quads",
    "Secondary Muscles": "Glutes, Core, Upper Back",
    "Exercise Type": "Compound",
    "Equipment": "Landmine",
    "Workout Type": "Lower Body Strength",
    "Progression": "Progressive Overload"
  },
  {
    "Exercise Name": "Lat Pulldown",
    "Primary Muscle": "Lats",
    "Secondary Muscles": "Biceps, Rear Delts, Traps",
    "Exercise Type": "Compound",
    "Equipment": "Cable Machine",
    "Workout Type": "Upper Body Strength, Push/Pull/Legs",
    "Progression": "Progressive Overload",
    "Webp File": "lat-pulldown.webp"
  },

  {
    "Exercise Name": "Lateral Lunge",
    "Primary Muscle": "Quads",
    "Secondary Muscles": "Adductors, Abductors, Glutes",
    "Exercise Type": "Compound",
    "Equipment": "Bodyweight",
    "Workout Type": "Lower Body Strength",
    "Progression": "Progressive Overload"
  },
  {
    "Exercise Name": "Leg Raise",
    "Primary Muscle": "Core",
    "Secondary Muscles": "Hip Flexors",
    "Exercise Type": "Isolation",
    "Equipment": "Bodyweight",
    "Workout Type": "Core",
    "Progression": "Progressive Overload"
  },

  {
    "Exercise Name": "Lunge",
    "Primary Muscle": "Quads",
    "Secondary Muscles": "Glutes, Hamstrings, Core",
    "Exercise Type": "Compound",
    "Equipment": "Bodyweight",
    "Workout Type": "Lower Body Strength",
    "Progression": "Progressive Overload",
    "Webp File": "lunge.webp"
  },
  {
    "Exercise Name": "Mountain Climber",
    "Primary Muscle": "Core",
    "Secondary Muscles": "Shoulders, Hip Flexors, Quads",
    "Exercise Type": "Compound",
    "Equipment": "Bodyweight",
    "Workout Type": "Cardio, HIIT",
    "Progression": "Power Development"
  },

  {
    "Exercise Name": "Oblique Crunch",
    "Primary Muscle": "Obliques",
    "Secondary Muscles": "Core",
    "Exercise Type": "Isolation",
    "Equipment": "Bodyweight",
    "Workout Type": "Core",
    "Progression": "Progressive Overload"
  },

  {
    "Exercise Name": "Plank",
    "Primary Muscle": "Core",
    "Secondary Muscles": "Shoulders, Chest, Triceps",
    "Exercise Type": "Compound",
    "Equipment": "Bodyweight",
    "Workout Type": "Core",
    "Progression": "Progressive Overload"
  },
  {
    "Exercise Name": "Plank Jack",
    "Primary Muscle": "Core",
    "Secondary Muscles": "Shoulders, Quads, Glutes",
    "Exercise Type": "Compound",
    "Equipment": "Bodyweight",
    "Workout Type": "Core, HIIT",
    "Progression": "Progressive Overload"
  },
 
  {
    "Exercise Name": "Pogo Hop",
    "Primary Muscle": "Calves",
    "Secondary Muscles": "Quads, Core",
    "Exercise Type": "Compound",
    "Equipment": "Bodyweight",
    "Workout Type": "Cardio, HIIT",
    "Progression": "Power Development"
  },
  {
    "Exercise Name": "Pull-Up",
    "Primary Muscle": "Lats",
    "Secondary Muscles": "Biceps, Core, Delts",
    "Exercise Type": "Compound",
    "Equipment": "Bodyweight",
    "Workout Type": "Upper Body Strength, Full Body Strength",
    "Progression": "Progressive Overload",
    "Webp File": "pull-up.webp"
  },
  {
    "Exercise Name": "Push-Up",
    "Primary Muscle": "Chest",
    "Secondary Muscles": "Triceps, Front Delts",
    "Exercise Type": "Compound",
    "Equipment": "Bodyweight",
    "Workout Type": "Upper Body Strength, Full Body Strength",
    "Progression": "Progressive Overload",
    "Webp File": "push-up.webp"
  },
  {
    "Exercise Name": "Rainbow Crunches",
    "Primary Muscle": "Core",
    "Secondary Muscles": "Obliques",
    "Exercise Type": "Compound",
    "Equipment": "Bodyweight",
    "Workout Type": "Core",
    "Progression": "Progressive Overload"
  },
  {
    "Exercise Name": "Reverse Grip Pulldown",
    "Webp File": "reverse-grip-pulldown.webp",
    "Primary Muscle": "Lats",
    "Secondary Muscles": "Biceps, Core",
    "Exercise Type": "Compound",
    "Equipment": "Cable Machine",
    "Workout Type": "Upper Body Strength",
    "Progression": "Progressive Overload"
  },
  {
    "Exercise Name": "Reverse Lunge",
    "Primary Muscle": "Quads",
    "Secondary Muscles": "Glutes, Hamstrings, Core",
    "Exercise Type": "Compound",
    "Equipment": "Bodyweight",
    "Workout Type": "Lower Body Strength",
    "Progression": "Progressive Overload"
  },
 
  {
    "Exercise Name": "Rope Pulldown",
    "Webp File": "rope-pulldown.webp",
    "Primary Muscle": "Lats",
    "Secondary Muscles": "Biceps, Core",
    "Exercise Type": "Compound",
    "Equipment": "Cable Machine",
    "Workout Type": "Upper Body Strength",
    "Progression": "Progressive Overload"
  },
  {
    "Exercise Name": "Rope Tricep Extension",
    "Primary Muscle": "Triceps",
    "Secondary Muscles": "Chest, Front Delts",
    "Exercise Type": "Isolation",
    "Equipment": "Cable Machine",
    "Workout Type": "Upper Body Strength",
    "Progression": "Progressive Overload"
  },
  {
    "Exercise Name": "Russian Twist",
    "Primary Muscle": "Core",
    "Secondary Muscles": "Obliques, Hip Flexors",
    "Exercise Type": "Compound",
    "Equipment": "Bodyweight",
    "Workout Type": "Core",
    "Progression": "Progressive Overload"
  },
  {
    "Exercise Name": "Scissor Kicks",
    "Primary Muscle": "Core",
    "Secondary Muscles": "Hip Flexors",
    "Exercise Type": "Isolation",
    "Equipment": "Bodyweight",
    "Workout Type": "Core",
    "Progression": "Progressive Overload"
  },
  {
    "Exercise Name": "Seated Cable Row",
    "Primary Muscle": "Lats",
    "Secondary Muscles": "Traps, Rhomboids, Biceps, Rear Delts",
    "Exercise Type": "Compound",
    "Equipment": "Cable Machine",
    "Workout Type": "Upper Body Strength, Push/Pull/Legs",
    "Progression": "Progressive Overload",
    "Webp File": "seated-cable-row.webp"
  },
  {
    "Exercise Name": "Side Plank",
    "Primary Muscle": "Obliques",
    "Secondary Muscles": "Core, Shoulders",
    "Exercise Type": "Compound",
    "Equipment": "Bodyweight",
    "Workout Type": "Core",
    "Progression": "Progressive Overload"
  },
  {
    "Exercise Name": "Single-Leg Glute Bridge",
    "Primary Muscle": "Glutes",
    "Secondary Muscles": "Hamstrings, Core",
    "Exercise Type": "Compound",
    "Equipment": "Bodyweight",
    "Workout Type": "Lower Body Strength",
    "Progression": "Progressive Overload"
  },


  {
    "Exercise Name": "Slam Ball Rotational Slam",
    "Primary Muscle": "Core",
    "Secondary Muscles": "Obliques, Delts, Hamstrings",
    "Exercise Type": "Compound",
    "Equipment": "Slam Ball",
    "Workout Type": "Core, HIIT, Cardio",
    "Progression": "Power Development"
  },
  {
    "Exercise Name": "Slam Ball Slam",
    "Primary Muscle": "Core",
    "Secondary Muscles": "Delts, Hamstrings, Glutes",
    "Exercise Type": "Compound",
    "Equipment": "Slam Ball",
    "Workout Type": "Full Body Strength, HIIT, Cardio",
    "Progression": "Power Development"
  },
  {
    "Exercise Name": "Slam Ball Squat",
    "Primary Muscle": "Quads",
    "Secondary Muscles": "Glutes, Core",
    "Exercise Type": "Compound",
    "Equipment": "Slam Ball",
    "Workout Type": "Lower Body Strength",
    "Progression": "Progressive Overload"
  },
  {
    "Exercise Name": "Slamball Squat",
    "Webp File": "slamball-squat.webp",
    "Primary Muscle": "Quads",
    "Secondary Muscles": "Glutes, Hamstrings, Core",
    "Exercise Type": "Compound",
    "Equipment": "Bodyweight",
    "Workout Type": "Lower Body Strength",
    "Progression": "Progressive Overload"
  },
  {
    "Exercise Name": "Squat",
    "Primary Muscle": "Quads",
    "Secondary Muscles": "Glutes, Hamstrings, Core",
    "Exercise Type": "Compound",
    "Equipment": "Bodyweight",
    "Workout Type": "Lower Body Strength, Full Body Strength",
    "Progression": "Progressive Overload"
  },

  {
    "Exercise Name": "Straight Arm Lat Pulldown",
    "Webp File": "straight-arm-lat-pulldown.webp",
    "Primary Muscle": "Lats",
    "Secondary Muscles": "Biceps, Core",
    "Exercise Type": "Compound",
    "Equipment": "Cable Machine",
    "Workout Type": "Upper Body Strength",
    "Progression": "Progressive Overload"
  },
  {
    "Exercise Name": "Superman",
    "Primary Muscle": "Erector Spinae",
    "Secondary Muscles": "Glutes, Rear Delts",
    "Exercise Type": "Compound",
    "Equipment": "Bodyweight",
    "Workout Type": "Lower Body Strength",
    "Progression": "Progressive Overload"
  },
  {
    "Exercise Name": "T Bar Row",
    "Webp File": "t-bar-row.webp",
    "Primary Muscle": "Lats",
    "Secondary Muscles": "Biceps, Core",
    "Exercise Type": "Compound",
    "Equipment": "Bodyweight",
    "Workout Type": "Upper Body Strength",
    "Progression": "Progressive Overload"
  },


  {
    "Exercise Name": "V-Up",
    "Primary Muscle": "Core",
    "Secondary Muscles": "Hip Flexors, Chest",
    "Exercise Type": "Compound",
    "Equipment": "Bodyweight",
    "Workout Type": "Core",
    "Progression": "Progressive Overload"
  },
  {
    "Exercise Name": "Walking Lunge",
    "Primary Muscle": "Quads",
    "Secondary Muscles": "Glutes, Hamstrings, Core",
    "Exercise Type": "Compound",
    "Equipment": "Bodyweight",
    "Workout Type": "Lower Body Strength, HIIT",
    "Progression": "Progressive Overload"
  },
  {
    "Exercise Name": "Wall Sit",
    "Primary Muscle": "Quads",
    "Secondary Muscles": "Glutes, Core",
    "Exercise Type": "Compound",
    "Equipment": "Bodyweight",
    "Workout Type": "Lower Body Strength",
    "Progression": "Progressive Overload",
    "Webp File": "wall-sit.webp"
  },
  {
    "Exercise Name": "Woodchopper",
    "Primary Muscle": "Core",
    "Secondary Muscles": "Obliques, Delts",
    "Exercise Type": "Compound",
    "Equipment": "Bodyweight",
    "Workout Type": "Core",
    "Progression": "Progressive Overload"
  }
]
